odoo/addons/pos_global_discount_in_line/README.rst
odoo/addons/pos_global_discount_in_line/__init__.py
odoo/addons/pos_global_discount_in_line/__manifest__.py
odoo/addons/pos_global_discount_in_line/i18n/es.po
odoo/addons/pos_global_discount_in_line/i18n/fr.po
odoo/addons/pos_global_discount_in_line/i18n/it.po
odoo/addons/pos_global_discount_in_line/i18n/pos_global_discount_in_line.pot
odoo/addons/pos_global_discount_in_line/models/__init__.py
odoo/addons/pos_global_discount_in_line/models/pos_config.py
odoo/addons/pos_global_discount_in_line/readme/CONTRIBUTORS.rst
odoo/addons/pos_global_discount_in_line/readme/DESCRIPTION.rst
odoo/addons/pos_global_discount_in_line/readme/USAGE.rst
odoo/addons/pos_global_discount_in_line/static/description/icon.png
odoo/addons/pos_global_discount_in_line/static/description/index.html
odoo/addons/pos_global_discount_in_line/static/src/js/GlobalLineDiscount.js
odoo/addons/pos_global_discount_in_line/views/pos_discount_views.xml
odoo/addons/pos_global_discount_in_line/views/pos_templates.xml
odoo14_addon_pos_global_discount_in_line-14.0.1.0.1.dev10.dist-info/METADATA
odoo14_addon_pos_global_discount_in_line-14.0.1.0.1.dev10.dist-info/WHEEL
odoo14_addon_pos_global_discount_in_line-14.0.1.0.1.dev10.dist-info/top_level.txt
odoo14_addon_pos_global_discount_in_line-14.0.1.0.1.dev10.dist-info/RECORD
