Metadata-Version: 2.1
Name: odoo14-addon-pos_global_discount_in_line
Version: 14.0.1.0.1.dev10
Summary: Order discount in line instead of discount product
Home-page: https://github.com/OCA/pos
Author: Ilyas, Ooops404, Odoo Community Association (OCA)
Author-email: support@odoo-community.org
License: AGPL-3
Classifier: Programming Language :: Python
Classifier: Framework :: Odoo
Classifier: Framework :: Odoo :: 14.0
Classifier: License :: OSI Approved :: GNU Affero General Public License v3
Requires-Python: >=3.6
Requires-Dist: odoo<14.1dev,>=14.0a
